virtualenvapi/__init__.py
virtualenvapi/exceptions.py
virtualenvapi/manage.py
virtualenvapi/util.py
virtualenv_api-2.1.18.dist-info/AUTHORS
virtualenv_api-2.1.18.dist-info/LICENSE
virtualenv_api-2.1.18.dist-info/METADATA
virtualenv_api-2.1.18.dist-info/WHEEL
virtualenv_api-2.1.18.dist-info/top_level.txt
virtualenv_api-2.1.18.dist-info/RECORD
